openai_api_polling/__init__.py
openai_api_polling/core/__init__.py
openai_api_polling/core/openai_resources.py
openai_api_polling/polling/__init__.py
openai_api_polling/polling/api_polling.py
openai_api_polling/polling/client_polling.py
openai_api_polling/utils/__init__.py
openai_api_polling/utils/count_token.py
openai_api_polling-0.1.5.dist-info/METADATA
openai_api_polling-0.1.5.dist-info/WHEEL
openai_api_polling-0.1.5.dist-info/entry_points.txt
openai_api_polling-0.1.5.dist-info/RECORD
