Metadata-Version: 2.4
Name: openai-api-polling
Version: 0.1.5
Summary: Polling OpenAI API without rate limit issues.
Project-URL: Homepage, https://github.com/sepinetam/openai-api-polling
Project-URL: Source, https://github.com/sepinetam/openai-api-polling
Author-email: SongTan <sepinetam@gmail.com>
Requires-Python: >=3.11
Requires-Dist: anthropic>=0.75.0
Requires-Dist: google-genai>=1.55.0
Requires-Dist: openai>=2.0.0
Requires-Dist: tiktoken>=0.10.0
